libvna-0.2.2.dist-info/RECORD
libvna-0.2.2.dist-info/LICENSE
libvna-0.2.2.dist-info/METADATA
libvna-0.2.2.dist-info/WHEEL
libvna.libs/libvna-da643bea.so.0.0.0
libvna.libs/libyaml-0-1bf300b2.so.2.0.4
libvna/data.cpython-311-x86_64-linux-gnu.so
libvna/__init__.py
libvna/cal.cpython-311-x86_64-linux-gnu.so
libvna/conv.cpython-311-x86_64-linux-gnu.so
