Metadata-Version: 2.1
Name: libvna
Version: 0.2.2
Summary: Vector network analyzer calibration, load, store and convert
Keywords: Electronics,RF,S-Parameters,Test and Measurement,Touchstone,VNA
Author-Email: D Scott Guthridge <scott_guthridge@rompromity.net>
License:                     GNU GENERAL PUBLIC LICENSE
Classifier: Intended Audience :: Science/Research
Classifier: Intended Audience :: Developers
Classifier: Programming Language :: C
Classifier: Programming Language :: Python
Classifier: Programming Language :: Python :: 3
Classifier: Programming Language :: Python :: 3.9
Classifier: Programming Language :: Python :: 3.10
Classifier: Programming Language :: Python :: 3.11
Classifier: Programming Language :: Python :: 3.12
Classifier: Programming Language :: Python :: 3.13
Classifier: Topic :: Software Development :: Libraries
Classifier: Topic :: Scientific/Engineering
Classifier: Operating System :: Microsoft :: Windows
Classifier: Operating System :: POSIX :: Linux
Classifier: Operating System :: POSIX
Classifier: Operating System :: Unix
Classifier: Operating System :: MacOS
Project-URL: Documentation, https://libvna.readthedocs.io/en/latest/
Project-URL: Repository, https://github.com/scott-guthridge/pylibvna
Requires-Python: >=3.10
Requires-Dist: numpy
Provides-Extra: test
Requires-Dist: unittest; extra == "test"
Provides-Extra: docs
Requires-Dist: sphinx; extra == "docs"
Requires-Dist: sphinx_rtd_theme; extra == "docs"
Requires-Dist: readthedocs-sphinx-search; extra == "docs"
